s3tui/__init__.py
s3tui/__main__.py
s3tui/app.py
s3tui/libs/__init__.py
s3tui/libs/s3_client.py
s3tui/ui/__init__.py
s3tui/ui/dialogs.py
s3tui/ui/list_view.py
s3tui/utils/__init__.py
s3tui/utils/clipboard.py
s3tui-0.1.0.dist-info/METADATA
s3tui-0.1.0.dist-info/WHEEL
s3tui-0.1.0.dist-info/entry_points.txt
s3tui-0.1.0.dist-info/top_level.txt
s3tui-0.1.0.dist-info/RECORD
